usinelib/__init__.py
usinelib-0.0.4.dist-info/LICENSE
usinelib-0.0.4.dist-info/METADATA
usinelib-0.0.4.dist-info/WHEEL
usinelib-0.0.4.dist-info/top_level.txt
usinelib-0.0.4.dist-info/RECORD
