Metadata-Version: 2.1
Name: usinelib
Version: 0.0.4
Summary: Fetch menu from usine.se
Home-page: https://github.com/misse/usinelib
Author: Martin Bergman
Author-email: martin@devsed.se
License: UNKNOWN
Platform: UNKNOWN
Classifier: Programming Language :: Python :: 3
Classifier: License :: OSI Approved :: GNU General Public License v3 (GPLv3)
Classifier: Operating System :: OS Independent
Requires-Python: >=3
